neuroschem/__init__.py
neuroschem-0.0.1a0.dist-info/licenses/LICENSE
neuroschem-0.0.1a0.dist-info/METADATA
neuroschem-0.0.1a0.dist-info/WHEEL
neuroschem-0.0.1a0.dist-info/top_level.txt
neuroschem-0.0.1a0.dist-info/RECORD
