Metadata-Version: 2.4
Name: neuroschem
Version: 0.0.1a0
Summary: AI-assisted schematic generation & validation
Author-email: Barry Wang <barry_wang02@163.com>
License: MIT License
Project-URL: homepage, https://github.com/Chutian-Wang/neuroschem
Project-URL: bug_tracker, https://github.com/Chutian-Wang/neuroschem/issues
Keywords: EDA,schematic,AI,netlist,auto-layout
Classifier: Development Status :: 2 - Pre-Alpha
Classifier: Intended Audience :: Developers
Classifier: License :: OSI Approved :: MIT License
Classifier: Programming Language :: Python :: 3
Classifier: Programming Language :: Python :: 3 :: Only
Classifier: Programming Language :: Python :: 3.9
Classifier: Topic :: Scientific/Engineering :: Electronic Design Automation (EDA)
Requires-Python: >=3.9
License-File: LICENSE
Requires-Dist: pydantic>=2.7
Requires-Dist: schemdraw>=0.20
Dynamic: license-file
